SSAP/SSAP.py
SSAP/__init__.py
SSAP/bsfcmap.py
SSAP-0.0.58.dist-info/LICENSE
SSAP-0.0.58.dist-info/METADATA
SSAP-0.0.58.dist-info/WHEEL
SSAP-0.0.58.dist-info/top_level.txt
SSAP-0.0.58.dist-info/RECORD
